{
  "941729574411173989": {
    "941883139301707777": {
      "p1": "252980043511234560",
      "state": "game",
      "p2": "770704587496882176",
      "ba": [
        ":one:",
        ":two:",
        ":three:",
        ":four:",
        ":five:",
        ":six:",
        ":seven:",
        ":eight:",
        ":nine:"
      ],
      "turn": "770704587496882176",
      "sign": "⭕",
      "sentmsg": {
        "channelId": "941883139301707777",
        "guildId": "941729574411173989",
        "id": "980578412752166952",
        "createdTimestamp": 1653858511866,
        "type": "DEFAULT",
        "system": false,
        "content": "The TicTacToe game between <@252980043511234560> and <@770704587496882176> has begun!\n\n**Current Turn:** ⭕ <@770704587496882176>",
        "authorId": "849276828819783681",
        "pinned": false,
        "tts": false,
        "nonce": null,
        "embeds": [],
        "components": [],
        "attachments": [],
        "stickers": [],
        "editedTimestamp": null,
        "webhookId": null,
        "groupActivityApplicationId": null,
        "applicationId": null,
        "activity": null,
        "flags": 0,
        "reference": null,
        "interaction": null,
        "cleanContent": "The TicTacToe game between @​krish and @​luke has begun!\n\n**Current Turn:** ⭕ @​luke"
      },
      "gamemsg": {
        "channelId": "941883139301707777",
        "guildId": "941729574411173989",
        "id": "980578413523927050",
        "createdTimestamp": 1653858512050,
        "type": "DEFAULT",
        "system": false,
        "content": ":one::two::three:\n:four::five::six:\n:seven::eight::nine:",
        "authorId": "849276828819783681",
        "pinned": false,
        "tts": false,
        "nonce": null,
        "embeds": [],
        "components": [],
        "attachments": [],
        "stickers": [],
        "editedTimestamp": null,
        "webhookId": null,
        "groupActivityApplicationId": null,
        "applicationId": null,
        "activity": null,
        "flags": 0,
        "reference": null,
        "interaction": null,
        "cleanContent": ":one::two::three:\n:four::five::six:\n:seven::eight::nine:"
      }
    }
  }
}